odoo9_addon_crm_lead_website-9.0.1.0.0-py2.7-nspkg.pth
odoo_addons/crm_lead_website/__openerp__.py
odoo_addons/crm_lead_website/__init__.py
odoo_addons/crm_lead_website/README.rst
odoo_addons/crm_lead_website/models/__init__.py
odoo_addons/crm_lead_website/models/crm_lead.py
odoo_addons/crm_lead_website/i18n/it.po
odoo_addons/crm_lead_website/i18n/es.po
odoo_addons/crm_lead_website/i18n/hr.po
odoo_addons/crm_lead_website/i18n/sl.po
odoo_addons/crm_lead_website/i18n/fr.po
odoo_addons/crm_lead_website/i18n/pt_BR.po
odoo_addons/crm_lead_website/views/crm_lead.xml
odoo_addons/crm_lead_website/tests/test_lead.py
odoo_addons/crm_lead_website/tests/__init__.py
odoo_addons/crm_lead_website/static/description/icon.png
odoo9_addon_crm_lead_website-9.0.1.0.0.dist-info/top_level.txt
odoo9_addon_crm_lead_website-9.0.1.0.0.dist-info/WHEEL
odoo9_addon_crm_lead_website-9.0.1.0.0.dist-info/RECORD
odoo9_addon_crm_lead_website-9.0.1.0.0.dist-info/metadata.json
odoo9_addon_crm_lead_website-9.0.1.0.0.dist-info/DESCRIPTION.rst
odoo9_addon_crm_lead_website-9.0.1.0.0.dist-info/METADATA
odoo9_addon_crm_lead_website-9.0.1.0.0.dist-info/namespace_packages.txt
